app/__init__.py
app/main.py
app/assets/screenshot-20250605-183118.png
app/assets/screenshot-20250605-183453.png
app/assets/screenshot-20250605-184012.png
app/utils/test.py
app/view/windows.py
syz_base_mac-0.0.15.dist-info/METADATA
syz_base_mac-0.0.15.dist-info/WHEEL
syz_base_mac-0.0.15.dist-info/entry_points.txt
syz_base_mac-0.0.15.dist-info/top_level.txt
syz_base_mac-0.0.15.dist-info/RECORD
