Metadata-Version: 2.4
Name: syz-base-mac
Version: 0.0.15
Requires-Python: >=3.6
Requires-Dist: PyQt6>=6.0.0
Dynamic: requires-dist
Dynamic: requires-python
